MTCFeatures/DataLocation.py
MTCFeatures/MTCFeatureLoader.py
MTCFeatures/__init__.py
MTCFeatures/appdirs.py
MTCFeatures-1.1.dist-info/LICENCE_Data
MTCFeatures-1.1.dist-info/LICENCE_Software
MTCFeatures-1.1.dist-info/METADATA
MTCFeatures-1.1.dist-info/WHEEL
MTCFeatures-1.1.dist-info/top_level.txt
MTCFeatures-1.1.dist-info/RECORD
