Metadata-Version: 2.1
Name: MTCFeatures
Version: 1.1
Summary: Melodies from Meertens Tune Collections and Essen Folksong Collection as sequences of features.
Home-page: https://github.com/pvankranenburg/MTCFeatures
Author: Peter van Kranenburg
Author-email: peter.van.kranenburg@meertens.knaw.nl
License: MIT
Keywords: Melody,Music,Features
Platform: UNKNOWN
Classifier: Programming Language :: Python :: 3
Classifier: License :: OSI Approved :: MIT License
Classifier: Operating System :: OS Independent
